MANIFEST.in
README.rst
setup.py
incisive/__init__.py
incisive/core.py
incisive.egg-info/PKG-INFO
incisive.egg-info/SOURCES.txt
incisive.egg-info/dependency_links.txt
incisive.egg-info/not-zip-safe
incisive.egg-info/top_level.txt