Metadata-Version: 1.1
Name: incisive
Version: 0.1.0
Summary: A tiny library for handling CSV files.
Home-page: https://github.com/TaurusOlson/incisive
Author: Taurus Olson
Author-email: taurusolson@gmail.com
License: MIT
Keywords: csv tools
Platform: UNKNOWN
Classifier: Programming Language :: Python :: 2.7
Classifier: Topic :: Utilities
